od_client/__init__.py
od_client/api_client.py
od_client/entities.py
od_client/enums.py
od_client/utils.py
od_client-0.1.0.dist-info/LICENSE
od_client-0.1.0.dist-info/WHEEL
od_client-0.1.0.dist-info/METADATA
od_client-0.1.0.dist-info/RECORD
